tcy/__init__.py
tcy/conftest.py
tcy/tcy.py
tcy/test_configs.json
tcy/test_tsv_file.py
tcy-0.0.0.dist-info/LICENSE
tcy-0.0.0.dist-info/METADATA
tcy-0.0.0.dist-info/WHEEL
tcy-0.0.0.dist-info/entry_points.txt
tcy-0.0.0.dist-info/top_level.txt
tcy-0.0.0.dist-info/RECORD
