Metadata-Version: 2.1
Name: tcy
Version: 0.0.0
Summary: A python package for converting tsv files into conda yml files
Author-email: Johannes Wiesner <joh.wiesner@gmail.com>
License: MIT
Project-URL: Homepage, https://github.com/JohannesWiesner/tcy
Keywords: python,tsv,environment,conda,yml,tsv-parser
Classifier: Programming Language :: Python :: 3
Classifier: License :: OSI Approved :: MIT License
Classifier: Operating System :: OS Independent
License-File: LICENSE
Requires-Dist: numpy
Requires-Dist: pandas
Requires-Dist: pytest
